{
  "incumbent_ids": [
    363
  ],
  "rejected_config_ids": [
    7,
    11,
    173,
    191,
    200,
    227,
    267,
    280,
    288,
    314,
    364
  ],
  "incumbents_changed": 12,
  "trajectory": [
    {
      "config_ids": [
        7
      ],
      "costs": [
        0.1681399834665196
      ],
      "trial": 1,
      "walltime": 3.5684261322021484
    },
    {
      "config_ids": [
        11
      ],
      "costs": [
        0.16288233673188213
      ],
      "trial": 12,
      "walltime": 75.89152002334595
    },
    {
      "config_ids": [
        173
      ],
      "costs": [
        0.1576302011573436
      ],
      "trial": 168,
      "walltime": 831.7137107849121
    },
    {
      "config_ids": [
        191
      ],
      "costs": [
        0.13869936621658874
      ],
      "trial": 184,
      "walltime": 933.2617044448853
    },
    {
      "config_ids": [
        200
      ],
      "costs": [
        0.13135298980435373
      ],
      "trial": 197,
      "walltime": 998.591833114624
    },
    {
      "config_ids": [
        227
      ],
      "costs": [
        0.1282006062276111
      ],
      "trial": 223,
      "walltime": 1113.8002650737762
    },
    {
      "config_ids": [
        267
      ],
      "costs": [
        0.1229429594929734
      ],
      "trial": 266,
      "walltime": 1330.583086013794
    },
    {
      "config_ids": [
        280
      ],
      "costs": [
        0.10928630476715351
      ],
      "trial": 280,
      "walltime": 1396.2382950782776
    },
    {
      "config_ids": [
        288
      ],
      "costs": [
        0.10613392119041054
      ],
      "trial": 289,
      "walltime": 1425.0502200126648
    },
    {
      "config_ids": [
        314
      ],
      "costs": [
        0.09457150730228714
      ],
      "trial": 319,
      "walltime": 1557.7393774986267
    },
    {
      "config_ids": [
        364
      ],
      "costs": [
        0.08931386056764945
      ],
      "trial": 360,
      "walltime": 1738.3370418548584
    },
    {
      "config_ids": [
        363
      ],
      "costs": [
        0.089302838247451
      ],
      "trial": 364,
      "walltime": 1756.1401743888855
    }
  ],
  "state": {
    "queue": [
      [
        371,
        2
      ],
      [
        372,
        2
      ],
      [
        376,
        2
      ],
      [
        377,
        2
      ],
      [
        378,
        2
      ],
      [
        379,
        2
      ],
      [
        380,
        2
      ],
      [
        381,
        2
      ],
      [
        382,
        2
      ],
      [
        383,
        2
      ],
      [
        384,
        2
      ],
      [
        385,
        2
      ],
      [
        386,
        2
      ],
      [
        387,
        2
      ],
      [
        388,
        2
      ],
      [
        389,
        1
      ]
    ]
  }
}